ziloreapi/__init__.py
ziloreapi/api.py
ziloreapi/test.py
python_zilore-0.0.4.dist-info/LICENSE
python_zilore-0.0.4.dist-info/METADATA
python_zilore-0.0.4.dist-info/WHEEL
python_zilore-0.0.4.dist-info/top_level.txt
python_zilore-0.0.4.dist-info/RECORD
